{
   "Name": "jhbv",
   "Digimon": [
      {
         "name": "Growmon",
         "field": "Dragon's Roar",
         "attribute": "Virus",
         "level": "adult",
         "speed": 2.5,
         "sprites": null,
         "frame": 10,
         "feeding_time": 10,
         "exp": 0,
         "next_level": 10,
         "hunger": -2,
         "state": "Starving",
         "hit": [
            980,
            780,
            16,
            16
         ],
         "target": [
            1008,
            816,
            20,
            20
         ],
         "energy": 100,
         "facing": -1,
         "debug": false,
         "counter": 9,
         "feeding_area": [
            500,
            400,
            100,
            100
         ],
         "health": 1,
         "attack": 1,
         "coll": 0
      },
      {
         "name": "Gigimon",
         "field": "Dragon's Roar",
         "attribute": "Virus",
         "level": "baby_II",
         "speed": 1.4210854715202004e-13,
         "sprites": null,
         "frame": 10,
         "feeding_time": -1,
         "exp": 6,
         "next_level": 10,
         "hunger": -45,
         "state": "Starving",
         "hit": [
            463,
            768,
            16,
            16
         ],
         "target": [
            500,
            400,
            20,
            20
         ],
         "energy": 99,
         "facing": 1,
         "debug": false,
         "counter": 0,
         "feeding_area": [
            500,
            400,
            100,
            100
         ],
         "health": 1,
         "attack": 1,
         "coll": 1
      },
      {
         "name": "Yaamon",
         "field": "Nightmare Soldiers",
         "attribute": "Virus",
         "level": "baby_II",
         "speed": 0.15625,
         "sprites": null,
         "frame": 9,
         "feeding_time": 3,
         "exp": 2,
         "next_level": 10,
         "hunger": -5,
         "state": "Starving",
         "hit": [
            756,
            470,
            16,
            16
         ],
         "target": [
            500,
            400,
            20,
            20
         ],
         "energy": 77,
         "facing": -1,
         "debug": false,
         "counter": -1,
         "feeding_area": [
            500,
            400,
            100,
            100
         ],
         "health": 1,
         "attack": 1,
         "coll": 2
      },
      {
         "name": "Impmon",
         "field": "Nightmare Soldiers",
         "attribute": "Virus",
         "level": "child",
         "speed": 2.5,
         "sprites": null,
         "frame": 8,
         "feeding_time": 10,
         "exp": 3,
         "next_level": 10,
         "hunger": 27,
         "state": "Attack",
         "hit": [
            982,
            774,
            16,
            16
         ],
         "target": [
            1018,
            774,
            20,
            20
         ],
         "energy": 99,
         "facing": 1,
         "debug": false,
         "counter": 7,
         "feeding_area": [
            500,
            400,
            100,
            100
         ],
         "health": 1,
         "attack": 1,
         "coll": 0
      },
      {
         "name": "Guilmon",
         "field": "Dragon's Roar",
         "attribute": "Virus",
         "level": "child",
         "speed": 2.5,
         "sprites": null,
         "frame": 10,
         "feeding_time": 9,
         "exp": 0,
         "next_level": 10,
         "hunger": -2,
         "state": "Starving",
         "hit": [
            757,
            781,
            16,
            16
         ],
         "target": [
            753,
            809,
            20,
            20
         ],
         "energy": 100,
         "facing": 1,
         "debug": false,
         "counter": 9,
         "feeding_area": [
            500,
            400,
            100,
            100
         ],
         "health": 1,
         "attack": 1,
         "coll": 4
      },
      {
         "name": "Yaamon",
         "field": "Nightmare Soldiers",
         "attribute": "Virus",
         "level": "baby_II",
         "speed": 2.980232238769531e-07,
         "sprites": null,
         "frame": 10,
         "feeding_time": 10,
         "exp": 0,
         "next_level": 10,
         "hunger": -25,
         "state": "Starving",
         "hit": [
            677,
            150,
            16,
            16
         ],
         "target": [
            500,
            400,
            20,
            20
         ],
         "energy": 77,
         "facing": -1,
         "debug": false,
         "counter": 2,
         "feeding_area": [
            500,
            400,
            100,
            100
         ],
         "health": 1,
         "attack": 1,
         "coll": 5
      },
      {
         "name": "Gigimon",
         "field": "Dragon's Roar",
         "attribute": "Virus",
         "level": "baby_II",
         "speed": 0.001220703125,
         "sprites": null,
         "frame": 10,
         "feeding_time": 3,
         "exp": 0,
         "next_level": 10,
         "hunger": -13,
         "state": "Starving",
         "hit": [
            653,
            397,
            16,
            16
         ],
         "target": [
            500,
            400,
            20,
            20
         ],
         "energy": 89,
         "facing": -1,
         "debug": false,
         "counter": 2,
         "feeding_area": [
            500,
            400,
            100,
            100
         ],
         "health": 1,
         "attack": 1,
         "coll": 6
      },
      {
         "name": "Kiimon",
         "field": "Nightmare Soldiers",
         "attribute": "Virus",
         "level": "baby_I",
         "speed": 0.625,
         "sprites": null,
         "frame": 9,
         "feeding_time": 5,
         "exp": 7,
         "next_level": 10,
         "hunger": -3,
         "state": "Starving",
         "hit": [
            732,
            576,
            16,
            16
         ],
         "target": [
            775,
            607,
            20,
            20
         ],
         "energy": 29,
         "facing": 1,
         "debug": false,
         "counter": 2,
         "feeding_area": [
            500,
            400,
            100,
            100
         ],
         "health": 1,
         "attack": 1,
         "coll": 7
      },
      {
         "name": "Gigimon",
         "field": "Dragon's Roar",
         "attribute": "Virus",
         "level": "baby_II",
         "speed": 5,
         "sprites": null,
         "frame": 0,
         "feeding_time": 10,
         "exp": 0,
         "next_level": 10,
         "hunger": 18,
         "state": "Walking",
         "hit": [
            492,
            579,
            16,
            16
         ],
         "target": [
            463,
            577,
            20,
            20
         ],
         "energy": 18,
         "facing": -1,
         "debug": false,
         "counter": 7,
         "feeding_area": [
            500,
            400,
            100,
            100
         ],
         "health": 1,
         "attack": 1,
         "coll": 8
      }
   ],
   "Food": -1
}